{
  "@context": "http://iiif.io/api/presentation/2/context.json",
  "@id": "https://geniza.princeton.edu/annotations/search/?uri=https%3A%2F%2Fcudl.lib.cam.ac.uk%2Fiiif%2FMS-OR-01080-J-00095%2Fcanvas%2F1&manifest=https%3A%2F%2Fgeniza.princeton.edu%2Fdocuments%2F5555%2Fiiif%2Fmanifest%2F",
  "@type": "sc:AnnotationList",
  "resources": [
    {
      "etag": "\"f40abdacbfb256e2c682236266915fe9\"",
      "id": "https://geniza.princeton.edu/annotations/db6261a4-d168-4769-924a-c0e5f8340b93/",
      "type": "Annotation",
      "created": "2022-10-07T02:01:17.284335+00:00",
      "modified": "2025-04-25T00:28:46.451075+00:00",
      "dc:source": "https://geniza.princeton.edu/sources/1120/",
      "target": {
        "source": {
          "id": "https://cudl.lib.cam.ac.uk/iiif/MS-OR-01080-J-00095/canvas/1",
          "type": "Canvas",
          "partOf": {
            "id": "https://geniza.princeton.edu/documents/5555/iiif/manifest/"
          }
        },
        "selector": {
          "type": "FragmentSelector",
          "value": "xywh=pixel:256.06787109375,6269.07080078125,1760.402099609375,2197.43505859375",
          "conformsTo": "http://www.w3.org/TR/media-frags/"
        }
      },
      "body": [
        {
          "type": "TextualBody",
          "label": "recto (IB III,21 - section \u05d0)",
          "value": "<ol>\n<li>[\u05d0\u05dc]\u05e0\u05d0\u05db\u05d5\u05d3\u05d4 \u05d0\u05d1\u05d5 \u05e2\u05d1\u05d3 \u05d0\u05dc\u05dc\u05d4</li>\n<li>[\u05dc]\u05d4 \u05d7 \u05d0\u05d1\u05d4\u05e8\u05d0 \u05e4\u05dc\u05e4\u05dc \u05d1\u05e2\u05d3\u05dc</li>\n<li>[\u05ea\u05de]\u05e0\u05d4 \u05e0\u05d5 \u05de\u05ea\u05e7\u05d0\u05dc \u05d5\u05dc\u05d4 \u05db\u05d1</li>\n<li>\u05de\u05ea\u05e7\u05d0\u05dc \u05d7\u05e1\u05d0\u05d1 \u05ea\u05e4\u05d0\u05e8\u05d9\u05e7 \u05d5\u05dc\u05d4</li>\n<li>\u05d5\u05dc\u05d4 (!) \u05e7\u05d9\u05de\u05d4 \u05d1\u05d4\u05d0\u05e8\u05d9\u05df \u05d7\u05d3\u05d9\u05d3 \u27e6\u05d5\u05d1\u05d4\u05d0\u05e8\u05d9\u05df\u27e7</li>\n<li>[\u05d5]\u05e1\u05ea \u05d5\u05de\u05d0\u05d9\u05ea\u05d9\u05df \u05d1\u05d9\u05e6\u05d4 \u05d9\u05d5 \u05de\u05ea\u05e7\u05d0\u05dc</li>\n<li>[\u05d0\u05dc]\u05d2\u05de\u05dc\u05d4 \u05e6\u05d3 \u05de\u05ea\u05e7\u05d0\u05dc</li>\n<li>[\u05d5\u05dc\u05d4 \u05d9\u05d0] \u05de\u05ea\u05e7\u05d0\u05dc \u05d5\u05e0\u05e6\u05e3 \u05ea\u05e4\u05d0\u05e8\u05d9\u05e7 \u05e4\u05d9 \u05ea\u05d0\u05e0\u05d9</li>\n<li>[\u05d7\u05e1\u05d0\u05d1] \u05d0\u05dc\u05d2\u05de\u05dc\u05ea\u05d9\u05df \u05e7 \u05de\u05ea\u05e7\u05d0\u05dc</li>\n<li>\u05d5\u05d4 \u05de\u05ea\u05e7\u05d0\u05d9\u05dc(!) \u05d5\u05e0\u05e6\u05e3</li>\n<li>\u05e2\u05e0\u05d3\u05d4 \u05e7\u05e4\u05d5 \u05de\u05ea\u05e7\u05d0\u05dc \u05d0\u05dc\u05d1\u05d0\u05e7\u05d9</li>\n<li>\u05e2\u05e0\u05d3\u05d4 \u05e4 \u05de\u05ea\u05e7\u05d0\u05dc \u05d5\u05e0\u05e6\u05e3</li>\n<li>\u05d0\u05dc\u05d1\u05d0\u05e7\u05d9 \u05e2\u05e0\u05d3\u05d4 \u05e4 \u05de\u05ea\u05e7\u05d0\u05dc \u05d5\u05e0\u05e6\u05e3</li>\n</ol>",
          "format": "text/html",
          "TextInput": "rtl"
        }
      ],
      "motivation": [
        "sc:supplementing",
        "transcribing"
      ],
      "schema:position": 1
    },
    {
      "etag": "\"23aa7fc3b582bd3af8f94a66219fe03a\"",
      "id": "https://geniza.princeton.edu/annotations/da0bac07-7f4e-4acd-ad50-958e1ded8438/",
      "type": "Annotation",
      "created": "2025-04-25T00:35:34.454185+00:00",
      "modified": "2025-04-25T00:35:34.454199+00:00",
      "dc:source": "https://geniza.princeton.edu/sources/8/",
      "target": {
        "source": {
          "id": "https://cudl.lib.cam.ac.uk/iiif/MS-OR-01080-J-00095/canvas/1",
          "type": "Canvas",
          "partOf": {
            "id": "https://geniza.princeton.edu/documents/5555/iiif/manifest/"
          }
        },
        "selector": {
          "type": "FragmentSelector",
          "value": "xywh=pixel:264.43096923828125,5935.244140625,1883.7418823242188,2729.0107421875",
          "conformsTo": "http://www.w3.org/TR/media-frags/"
        }
      },
      "body": [
        {
          "type": "TextualBody",
          "label": "recto (section i)",
          "value": "<ol>\n<li>[The] n\u0101khud\u0101 Ab\u016b \u02bfAbd All\u0101h.\u00a0</li>\n<li>His credit: eight bah\u0101rs of pepper in one bale.</li>\n<li>Price: 56 mithq\u0101ls. And his credit: 22</li>\n<li>mithq\u0101ls on account of specific goods {alt. tr.: retail goods}.</li>\n<li>And his credit: the price of two bah\u0101rs of iron \u27e6and of two bah\u0101rs\u27e7</li>\n<li>[and] two hundred [and si]x \u2018eggs,\u2019 16 mithq\u0101ls.</li>\n<li>Total: 94 mithq\u0101ls.</li>\n<li>[His credit: eleven] and a half mithq\u0101ls for specific goods {alt. tr.: retail goods}, in a second</li>\n<li>account. The combined total: 105 \u00bd\u00a0</li>\n<li>mithq\u0101ls.</li>\n<li>His debit: 186 mithq\u0101ls. Balance</li>\n<li>of his debit: 80 \u00bd mithq\u0101ls.</li>\n<li>Balance of his debit: 80 \u00bd mithqals.</li>\n</ol>",
          "format": "text/html"
        }
      ],
      "motivation": [
        "sc:supplementing",
        "translating"
      ],
      "schema:position": 1
    },
    {
      "etag": "\"f9e25bd5c0defc2d1cae48cd2a42de70\"",
      "id": "https://geniza.princeton.edu/annotations/0943d6d3-0d70-457f-b287-61030b894b32/",
      "type": "Annotation",
      "created": "2022-10-07T02:01:17.290778+00:00",
      "modified": "2025-04-25T00:31:36.739942+00:00",
      "dc:source": "https://geniza.princeton.edu/sources/1120/",
      "target": {
        "source": {
          "id": "https://cudl.lib.cam.ac.uk/iiif/MS-OR-01080-J-00095/canvas/1",
          "type": "Canvas",
          "partOf": {
            "id": "https://geniza.princeton.edu/documents/5555/iiif/manifest/"
          }
        },
        "selector": {
          "type": "FragmentSelector",
          "value": "xywh=pixel:111.19550323486328,146.17616271972656,1963.9680709838867,1920.0601654052734",
          "conformsTo": "http://www.w3.org/TR/media-frags/"
        }
      },
      "body": [
        {
          "type": "TextualBody",
          "label": "recto (IB III,21 - section \u05d1)",
          "value": "<ol>\n<li>[...] \u05d0\u05dc\u05d3\u05d9 \u05d3\u05e4\u05e2\u05ea \u05d0\u05dc\u05d9</li>\n<li>\u05d0\u05dc\u05e0\u05d0\u05db\u05d5\u05d3\u05d4 \u05d0\u05d1\u05d5 [\u05e2]\u05d1\u05d3 \u05d0\u05dc\u05dc\u05d4 \u05d0\u05d1\u05df \u05d0\u05dc\u05db\u05ea\u05d0\u05d9\u05d1</li>\n<li>\u05de\u05df \u05d3\u05dc\u05da \u05d2 \u05d2\u05d7\u05d0\u05dc \u05e1\u05de\u05df \u05d5\u05d0\u05d9\u05e6\u05d0</li>\n<li>\u05d2\u05d7\u05dc\u05ea\u05d9\u05df \u05d5\u05d3\u05e1\u05ea\u05d9\u05df \u05e7\u05e8\u05d8\u05d0\u05e5 \u05db\u05d1\u05d0\u05e8</li>\n<li>\u05d5\u05d3 \u05de\u05db\u05d0\u05d3\u05d3 \u05d0\u05ea\u05e0\u05d9\u05df \u05d6\u05e0\u05d2\u05d1\u05d0\u05e8\u05d9\u05d4</li>\n<li>\u05d5\u05d0\u05ea\u05e0\u05d9\u05df \u05de\u05df \u05de\u05d7\u05d1\u05e1 \u05d2\u05d3\u05d9\u05d3 \u05d5\u05e2\u05e9\u05e8\u05d4</li>\n<li>\u05d7\u05d2\u05d0\u05e8 \u05d1\u05d6\u05d0\u05d3\u05d9 \u05d5\u05e4\u05e8\u05d0\u05e1\u05dc\u05ea\u05d9\u05df \u05ea\u05d5\u05dd</li>\n<li>\u05d5\u05d0\u05d9\u05e6\u05d0 \u05e4\u05d5\u05d8\u05d4 \u05de\u05e7\u05e6\u05d5\u05e8 \u05d0\u05dc\u05e7\u05d9\u05de\u05d4</li>\n<li>\u05d2 \u05d3\u05e0\u05d0 \u05d5\u05e0\u05e6\u05e3 //\u05d5\u05e8\u05d1\u05e2\\\\ \u05de\u05df \u05e2\u05d3\u05df \u05d5\u05e4\u05d5\u05d8\u05d4 \u05de\u05e0\u05d0\u05e8\u05d9</li>\n<li>\u05d0\u05dc\u05e7\u05d9\u05de\u05d4 \u05de\u05ea\u05e7\u05d0\u05dc \u05e4\u05d9\u05dc\u05d9 \u05d5\u05d0\u05d1\u05e8\u05d6\u05dd</li>\n<li>\u05e4\u05d9\u05d4 \u05de \u05db\u05e8\u05d6\u05d4 \u05e4\u05e6\u05d4 \u05d4 \u05d2\u05dc\u05d0\u05d2\u05dc</li>\n<li>\u05e7\u05d9\u05de\u05d4 \u05d0\u05dc\u05d4 \u05d2\u05d7\u05d0\u05dc \u05e1\u05de\u05df \u05d2 \u05de\u05ea\u05d0\u05e7\u05d9\u05dc</li>\n<li>\u05e4\u05d9\u05dc\u05d9\u05d0 \u05d5\u05e7\u05d9\u05de\u05d4 \u05d0\u05dc\u05d3\u05e1\u05ea\u05d9\u05df \u05db\u05d0\u05d2\u05d3 \u05de\u05ea\u05e7\u05d0\u05dc</li>\n<li>\u05d5\u05e7\u05d9\u05de\u05d4 \u05d0\u05dc\u05d3 \u05de\u05db\u05d0\u05d3\u05d3 \u05e0\u05e6\u05e3 \u05de\u05ea\u05e7\u05d0\u05dc</li>\n<li>\u05d5\u05e7\u05d9\u05de\u05d4 \u05e4\u05e8\u05d0\u05e1\u05dc\u05ea\u05d9\u05df \u05ea\u05d5\u05dd \u05e8\u05d1\u05e2 \u05de\u05ea\u05e7\u05d0\u05dc</li>\n<li>\u05d5\u05e7\u05d9\u05de\u05d4 \u05d9 \u05d0\u05d7\u05d2\u05d0\u05e8 \u05e8\u05d1\u05e2 \u05de\u05ea\u05e7\u05d0\u05dc</li>\n<li>[\u05d5\u05e7\u05d9]\u05de\u05d4 \u05d0\u05dc\u05db\u05e8\u05d6 \u05d0\u05dc\u05e4\u05e6\u05d4 \u05d5\u05d0\u05dc\u05d2\u05dc\u05d0\u05d2\u05dc</li>\n<li>\u05e0\u05e6\u05e3 \u05d5\u05e8\u05d1\u05e2 \u05d5\u05e7\u05d9\u05de\u05d4 [\u05d0\u05dc\u05e4]\u05d5\u05d8\u05d4 \u05de\u05e0\u05d0\u05e8\u05d9</li>\n<li>\u05de\u05ea\u05e7\u05d0\u05dc \u05d5\u05e7\u05d9\u05de\u05d4 \u05d0\u05dc\u05e4\u05d5\u05d8\u05d4 \u05e9\u05e2\u05e8\u05d9 \u05de\u05e7\u05e6\u05d5\u05e8</li>\n<li>\u05de\u05ea\u05e7\u05d0\u05dc \u05d5\u05e0\u05e6\u05e3 \u05d0\u05dc\u05d2\u05de\u05dc\u05d4 \u05d8 \u05de\u05ea\u05d0\u05e7\u05d9\u05dc</li>\n<li>\u05d2\u05d9\u05e8 \u05e8\u05d1\u05e2</li>\n<li>\u27e6\u05e4\u05dc\u05e4\u05dc\u27e7</li>\n<li>\u27e6\u05dc\u05d4 \u05e0\u05d5\u05dc \u27e6\u05d6\u27e7 \u05de\u05ea\u05d0\u05e7\u05d9\u05dc \u05d1\u05e2\u05d3 \u05d0\u05dc\u05d1\u05d0\u05e8\u05d1\u05d6\u05d0</li>\n<li>\u27e6\u05d5\u05d1\u05d9\u05d3\u05d4\u27e7 \u05d5\u05dc\u05d4 \u05d0\u05d9\u05e6\u05d0\u27e7</li>\n<li>\u05dc\u05d4 \u05e0\u05d5\u05dc \u05d7 \u05d0\u05d1\u05d4\u05e8\u05d0 \u05e4\u05dc\u05e4\u05dc \u05d9\u05db\u05e8\u05d2</li>\n<li>\u05de\u05e0\u05d4\u05d0 \u05d1\u05d4\u05d0\u05e8 \u05de\u05df \u05e7\u05d1\u05dc \u05d5\u05d0\u05dc\u05d3\u05d4 \u05e8\u05e1\u05dd</li>\n<li>\u05d5\u05d1\u05d4\u05d0\u05e8 \u05d1\u05d0\u05e8\u05d1\u05d6\u05d0 \u05d5\u05ea\u05d1\u05e7\u05d0 \u05dc\u05d4 \u05e1\u05ea\u05d4</li>\n<li>\u05de\u05ea\u05d0\u05e7\u05d9\u05dc \u05d5\u05dc\u05d4 \u05e0\u05d5\u05dc \u05d1\u05d4\u05d0\u05e8\u05d9\u05df \u05d7\u05d3\u05d9\u05d3</li>\n<li>\u05d5\u05d1\u05d4\u05d0\u05e8 \u05d1\u05d9\u05e5 \u05d2 \u05de\u05ea\u05d0\u05e7\u05d9\u05dc \u05d1\u05d0\u05dc \u05e2\u05e9\u05d5\u05e8</li>\n<li>\u05e4\u05d3\u05dc\u05da \u05d8 \u05de\u05ea\u05d0\u05e7\u05d9\u05dc \u05d5\u05e2\u05e0\u05d3\u05d4 \u05e0\u05d5\u05dc</li>\n<li>\u05d1\u05d4\u05d0\u05e8 \u05d7\u05d3\u05d9\u05d3 \u05de\u05df \u05e7\u05d1\u05dc \u05d5\u05d0\u05dc\u05d3\u05d4</li>\n</ol>",
          "format": "text/html",
          "TextInput": "rtl"
        }
      ],
      "motivation": [
        "sc:supplementing",
        "transcribing"
      ],
      "schema:position": 2
    },
    {
      "etag": "\"9d85a0daf50e67da4848d172753f5032\"",
      "id": "https://geniza.princeton.edu/annotations/cadd83f7-cfc1-4acd-9e8d-d71581b786d6/",
      "type": "Annotation",
      "created": "2025-04-25T00:36:03.370062+00:00",
      "modified": "2025-04-25T00:36:03.370077+00:00",
      "dc:source": "https://geniza.princeton.edu/sources/8/",
      "target": {
        "source": {
          "id": "https://cudl.lib.cam.ac.uk/iiif/MS-OR-01080-J-00095/canvas/1",
          "type": "Canvas",
          "partOf": {
            "id": "https://geniza.princeton.edu/documents/5555/iiif/manifest/"
          }
        },
        "selector": {
          "type": "FragmentSelector",
          "value": "xywh=pixel:47.07612991333008,90.81426239013672,1980.344036102295,5071.612983703613",
          "conformsTo": "http://www.w3.org/TR/media-frags/"
        }
      },
      "body": [
        {
          "type": "TextualBody",
          "label": "recto (section ii)",
          "value": "<ol>\n<li>I delivered to</li>\n<li>the n\u0101khud\u0101 Ab\u016b \u02bfAbd All\u0101h Ibn &lt;Abu&gt; \u02bel-Kat\u0101\u02beib:</li>\n<li>three water skins of melted butter and</li>\n<li>two other water skins; two dasts of large-sized paper;</li>\n<li>four cushions, two of Zanzibar type</li>\n<li>and two of new mi\u1e25bas; ten</li>\n<li>beryl stones; two far\u0101silas of garlic;</li>\n<li>also a \u2018fulled\u2019 f\u016b\u1e6da, worth</li>\n<li>3 \u00bd dinars \\\\and a quarter// from Aden; a Man\u0101r\u012b f\u016b\u1e6da</li>\n<li>worth a f\u012bl\u012b mithq\u0101l; a silk band</li>\n<li>with (?) {lit., \u2018in which are\u2019} forty silver beads, five little bells.\u00a0</li>\n<li>Price of the five water skins with melted butter, three f\u012bl\u012b</li>\n<li>mithq\u0101ls. Price of the two dasts of paper, one mithq\u0101l.</li>\n<li>Price of the four cushions, one half of a mithq\u0101l.</li>\n<li>Price of two far\u0101silas of garlic, \u00bc mithq\u0101l.</li>\n<li>Price of ten stones, one quarter of a mithq\u0101l.</li>\n<li>Price of the silver beads and the bells,</li>\n<li>three quarters. Price of the Man\u0101r\u012b f\u016b\u1e6da,</li>\n<li>one mithq\u0101l. Price of the woolen, \u2018fulled\u2019 f\u016b\u1e6da,</li>\n<li>one and a half mithq\u0101l. Total: nine mithq\u0101ls</li>\n<li>less one quarter.</li>\n<li>\u27e6Pepper</li>\n<li>His credit: \u27e67(?)\u27e7 mithq\u0101ls for freight after the b\u0101rbaz\u0101</li>\n<li>\u27e6and he received\u27e7 and also his credit\u27e7</li>\n<li>His credit: freight for eight bah\u0101rs of pepper, less</li>\n<li>one bah\u0101r duties paid for his father</li>\n<li>and one bah\u0101r b\u0101rbaz\u0101; balance in his credit, six</li>\n<li>mithq\u0101ls. His credit: freight for two bah\u0101rs of iron</li>\n<li>and one bah\u0101r of \u2018eggs,\u2019 three mithq\u0101ls, including the customs.</li>\n<li>Total: nine mithq\u0101ls. His debit: freight</li>\n<li>for one bah\u0101r of iron belonging to his father.</li>\n</ol>",
          "format": "text/html"
        }
      ],
      "motivation": [
        "sc:supplementing",
        "translating"
      ],
      "schema:position": 2
    }
  ]
}