{
  "@context": "http://iiif.io/api/presentation/2/context.json",
  "@id": "https://geniza.princeton.edu/annotations/search/?uri=https%3A%2F%2Fcudl.lib.cam.ac.uk%2Fiiif%2FMS-TS-00028-00022%2Fcanvas%2F1&manifest=https%3A%2F%2Fgeniza.princeton.edu%2Fdocuments%2F5358%2Fiiif%2Fmanifest%2F",
  "@type": "sc:AnnotationList",
  "resources": [
    {
      "id": "https://geniza.princeton.edu/annotations/d42027e3-841e-47da-8aab-ede79e92208e/",
      "type": "Annotation",
      "created": "2022-10-07T00:59:33.368017+00:00",
      "modified": "2022-10-07T00:59:33.368037+00:00",
      "dc:source": "https://geniza.princeton.edu/sources/751/",
      "target": {
        "source": {
          "id": "https://cudl.lib.cam.ac.uk/iiif/MS-TS-00028-00022/canvas/1",
          "type": "Canvas",
          "partOf": {
            "id": "https://geniza.princeton.edu/documents/5358/iiif/manifest/"
          }
        },
        "selector": {
          "type": "FragmentSelector",
          "value": "xywh=percent:1,1,98,98",
          "conformsTo": "http://www.w3.org/TR/media-frags/"
        }
      },
      "body": [
        {
          "type": "TextualBody",
          "label": "I, 14",
          "value": "<ol>\n<li>[...\u05de\u05e8]\u05e4\u05e2 \u05d5\u05d2\u05d8\u05d0 \u05d5[\u05d6\u05e0\u05d4 \u05e2\u05d7 \u05d5\u05e0\u05e6\u05e3 \u05de\u05d2\u05e1\u05dc ...]</li>\n<li>[\u05d5\u05d6\u05e0\u05d4 \u05d0\u05ea\u05e0\u05d9\u05df \u05d5\u05db]\u05de\u05e1\u05d9\u05df \u05d3\u05e8\u05d4\u05de\u05d0 \u05d5\u05e8\u05d1\u05e2 [...]</li>\n<li>[\u05d5\u05d6\u05df \u05d0\u05dc\u05db\u05dc \u05ea\u05dc]\u05ea \u05de\u05d0\u05d9\u05d4 \u05d5\u05ea\u05e1\u05e2\u05d4 \u05d5\u05db\u05de\u05e1\u05d9\u05df \u05d3\u05e8\u05d4\u05de[\u05d0 ...]</li>\n<li>[\u05d0\u05d1\u05d9 \u05d9\u05e2\u05e7\u05d5]\u05d1 \u05d0\u05dc\u05d7\u05db\u05d9\u05dd [... \u05d4\u05d3]\u05d4 \u05d0\u05dc\u05d0\u05d5\u05d6\u05d0\u05df \u05d0\u05de\u05dc\u05d0\u05d4[\u05d0 ...]</li>\n<li>\u05de\u05d5\u05dc\u05d0\u05d9 \u05d5\u05d9\u05ea\u05d7\u05e7\u05e7 \u05e4\u05d9 \u05d3\u05e4\u05ea\u05e8\u05d4 \u05d5\u05d0\u05dc\u05e6\u05e8\u05d4 \u05d0\u05dc\u05e0\u05d7[\u05d0\u05e1 ...]</li>\n<li>\u05d5\u05d1\u05e2\u05ea\u05d4 \u05d5\u05d0\u05db\u05d3\u05ea \u05e2\u05d5\u05e6\u05d4\u05d0 \u05e0\u05d7\u05d0\u05e1 \u05d1\u05ea\u05e8\u05d5\u05d4 \u05d2\u05de\u05d9\u05e2 \u05de[\u05d0 ...]</li>\n<li>\u05d0\u05d1\u05d9 \u05d9\u05e2\u05e7\u05d5\u05d1 \u05d5\u05e7\u05d3 \u05db\u05e0\u05ea \u05d0\u05e2\u05dc\u05de\u05ea \u05de\u05d5\u05dc\u05d0\u05d9 \u05d1\u05d3\u05dc\u05da \u05d5\u05d0\u05ea\u05d1[\u05ea\u05d4 \u05e4\u05d9 \u05d3\u05e4\u05ea\u05e8\u05d4 ... \u05d5\u05e7\u05d3]</li>\n<li>\u05e1\u05d0\u05dc\u05ea \u05de\u05d5\u05dc\u05d0\u05d9 \u05e4\u05d9 \u05d0\u05e1\u05dc\u05d0\u05e3 \u05e2\u05dc\u05d9 \u05db\u05de\u05e1\u05d9\u05df \u05d1\u05d4\u05d0\u05e8 \u05e4\u05dc\u05e4\u05dc \u05d5\u05e4\u05e2\u05dc[\u05ea\u05d4 \u05d5\u05e7\u05e1\u05de\u05ea \u05d0\u05dc\u05e1\u05dc\u05e3]</li>\n<li>\u05dc\u05de\u05e8\u05db\u05d1 \u05d0\u05dc\u05e7\u05de\u05d9 \u05d5\u05dc\u05de\u05e8\u05db\u05d1 \u05d1\u05d4\u05d6\u05d0\u05ea \u05d5\u05db\u05e8\u05d2\u05e0\u05d0 \u05d2\u05de\u05d9\u05e2\u05e0\u05d0 \u05e4\u05d9 [...]</li>\n<li>\u05d5\u05ea\u05e4\u05e6\u05dc\u05ea \u05d5\u05e0\u05d6\u05dc\u05ea \u05e9\u05d9\u05e2\u05ea\u05e0\u05d9 \u05e4\u05d9 \u05d0\u05dc\u05d1\u05d7\u05e8 \u05d5\u05de\u05d5\u05d0\u05dc\u05d9\u05d9 \u05d0\u05db\u05d5\u05ea\u05da [... \u05d5\u05d3\u05db\u05dc\u05ea]</li>\n<li>\u05d1\u05dc\u05d0\u05d3 \u05d0\u05dc\u05ea\u05d9\u05d6 \u05d5\u05e1\u05de\u05e2\u05ea \u05de\u05d0 \u05d2\u05e8\u05d9 \u05e2\u05dc\u05d9 \u05e4\u05d9 \u05d0\u05dc\u05ea\u05d9\u05d6 \u05d5\u05de\u05d0 \u05d5\u05d3\u05d9 [\u05d0\u05dc\u05d9 \u05d5\u05e6\u05d5\u05dc\u05d9 \u05d0\u05dc\u05d9 \u05e0\u05d4\u05e8]</li>\n<li>\u05d5\u05d0\u05e8\u05d4 \u05e1\u05d0\u05dc\u05dd \u05d1\u05d7\u05de\u05d3 \u05d0\u05dc\u05dc\u05d4 \u05ea\u05e2\u05d0\u05dc\u05d9 \u05d5\u05d5\u05e6\u05dc\u05e0\u05d9 \u05db\u05ea\u05d0\u05d1\u05da \u05d0\u05dc\u05d9 [\u05e0\u05d4\u05e8\u05d5\u05d0\u05e8\u05d4 \u05d5\u05e6\u05d7\u05d1\u05ea\u05d4]</li>\n<li>\u05d2\u05de\u05dc\u05d4 \u05d3\u05e0\u05d0\u05e0\u05d9\u05e8 \u05ea\u05e8\u05e1\u05dd \u05dc\u05d9 \u05d0\u05df \u05d0\u05d1\u05ea\u05d0\u05e2 \u05dc\u05da \u05e4\u05d9\u05dc\u05de\u05d0\u05df \u05d5\u05d1\u05d3[...]</li>\n<li>\u05d7\u05e8\u05d9\u05e8 \u05d5\u05de\u05d7\u05d0\u05d1\u05e1 \u05d7\u05de\u05e8 \u05d5\u05e1\u05d5\u05d3 \u05d5\u05d8\u05d1\u05e8\u05d9 \u05d5\u05de\u05db\u05d0\u05d3 \u05d5\u05d0\u05df \u05ea\u05d1[\u05e7\u05d9 ...]</li>\n<li>\u05d0\u05d6\u05e0\u05d4 \u05de\u05df \u05e2\u05e0\u05d3\u05d9 \u05d5\u05d0\u05e9\u05ea\u05e8\u05d9\u05ea \u05d7\u05d5\u05d0\u05d9\u05d2\u05da \u05d2\u05de\u05d9\u05e2\u05d4\u05d0 \u05de\u05df \u05de\u05d0\u05dc[\u05d9.... \u05d5\u05d0\u05dc\u05d3\u05e0\u05d0\u05e0\u05d9\u05e8]</li>\n<li>\u05d3\u05e4\u05e2\u05ea\u05d4 \u05dc\u05d3\u05d0\u05d3\u05d0 \u05d0\u05dc\u05d1\u05d9\u05d0\u05e2 \u05e2\u05dc\u05d9 \u05d6\u05d9\u05d0\u05d3\u05d4 \u05e8\u05d1\u05e2 \u05e4\u05d9 \u05d0\u05dc\u05d3\u05d9\u05e0[\u05d0\u05e8 ...]</li>\n<li>\u05d1\u05e2\u05d3 \u05d0\u05df \u05db\u05d0\u05e6\u05dd \u05d0\u05dc\u05d5\u05d6\u05d9\u05e8 \u05d5\u05d0\u05dc\u05d3\u05e0\u05d0\u05e0\u05d9\u05e8 \u05e2\u05e0\u05d3\u05d4 \u05d0\u05dc\u05d9 \u05d0\u05dc\u05d9\u05d5\u05dd [...]</li>\n<li>\u05d0\u05dc\u05d7\u05d5\u05d0\u05d9\u05d2 \u05d0\u05dc\u05de\u05db\u05ea\u05e6\u05d4 \u05d1\u05da \u05d5\u05d1\u05d0\u05db\u05d5\u05ea\u05da \u05d5\u05d2\u05e2\u05dc\u05ea \u05e4\u05d9 \u05d5\u05e1\u05d8\u05d4[\u05d0... \u05d5\u05db\u05ea\u05d1\u05ea \u05d0\u05dc\u05d9\u05da]</li>\n<li>\u05d5\u05e7\u05dc\u05ea \u05d9\u05d0\u05db\u05d3 \u05db\u05dc \u05de\u05e0\u05db\u05dd \u05e9\u05d4\u05d5\u05ea[[\u05e7]]\u05d4 \u05d5\u05d0\u05dc\u05d1\u05d0\u05e7\u05d9 \u05d9\u05d1\u05e7\u05d0 \u05dc\u05d9 \u05dc[... \u05d5\u05dc\u05d9]</li>\n<li>\u05d0\u05d9\u05e6\u05d0 \u05e6\u05e8\u05ea\u05d9\u05df \u05de\u05d7\u05d0\u05d1\u05e1 \u05d5\u05d0\u05e0\u05e4\u05d3\u05ea\u05d4\u05dd \u05de\u05e2 \u05d0\u05dc[...]</li>\n<li>\u05e1\u05d0\u05dc\u05de\u05d9\u05df \u05d5\u05d0\u05e2\u05dc\u05de\u05ea\u05da \u05d9\u05d0 \u05de\u05d5\u05dc\u05d0\u05d9 \u05d0\u05e0\u05e0\u05d9 \u05d8\u05d0\u05d9\u05e2 [... \u05d5\u05e4\u05d9 \u05d0\u05dc\u05d1\u05d7\u05e8 \u05e7\u05d3 \u05d2\u05e8\u05d9]</li>\n<li>\u05e2\u05dc\u05d9 \u05de\u05df \u05d0\u05dc\u05d0\u05d4\u05d5\u05d0\u05dc \u05de\u05d0 \u05e7\u05d3 \u05e2\u05e8\u05e4\u05ea\u05d4 \u05d5\u05de\u05d0 \u05db\u05e4\u05d9 [\u05e2\u05e0\u05da \u05d9\u05d0 \u05de\u05d5\u05dc\u05d0\u05d9 \u05d0\u05e0\u05e0\u05d9 \u05d5\u05e6\u05dc\u05ea]</li>\n<li>\u05d0\u05dc\u05d9 \u05de\u05e8\u05d1\u05d0\u05d8 \u05e1\u05d0\u05dc\u05de\u05d0 \u05d1\u05de\u05d0 \u05db\u05dc\u05e5 \u05de\u05df \u05de\u05d0\u05dc\u05d9 \u05d5\u05db\u05e0\u05ea [...]</li>\n<li>\u05d0\u05e0\u05e4\u05d3\u05ea\u05d4 \u05d0\u05dc\u05d9\u05db\u05dd \u05de\u05df \u05de\u05e8\u05d1\u05d0\u05d8 \u05e2\u05d5\u05e5 \u05de\u05df \u05de\u05d0\u05dc\u05db\u05dd [... \u05d5\u05db\u05ea\u05d1\u05ea]</li>\n<li>\u05d0\u05dc\u05d9\u05da \u05d0\u05e9\u05e8\u05d7 \u05dc\u05da \u05d7\u05d0\u05dc\u05d9 \u05d0\u05e1\u05d0\u05dc\u05da \u05e4\u05d9 \u05ea\u05e6\u05d7\u05d9\u05d7 //\u05ea\u05de\u05df \u05d2\u05de\u05d9\u05e2// \u05d0\u05dc\u05d7\u05d5\u05d0\u05d9\u05d2 [...]</li>\n<li>\u05d0\u05dc\u05de\u05e7\u05d3\u05dd \u05d3\u05db\u05e8\u05d4\u05d0 \u05d5\u05db\u05d3\u05dc\u05da \u05de\u05d0 \u05e6\u05d7 \u05e4\u05d9 \u05d0\u05dc\u05e0\u05d7\u05d0\u05e1 \u05d1\u05de\u05e2\u05d6[...]</li>\n<li>\u05d1\u05d4\u05d0\u05e8 \u05d5\u05db\u05e0\u05ea \u05e1\u05d0\u05dc\u05ea\u05da \u05d0\u05df \u05ea\u05d7\u05de\u05dc \u05dc\u05d9 \u05d0\u05dc\u05db\u05de\u05e1\u05d9\u05df \u05d1\u05d4\u05d0\u05e8 \u05d0\u05dc[\u05e4\u05dc\u05e4\u05dc...\u05de\u05e2 \u05de\u05d0]</li>\n<li>\u05db\u05d0\u05df \u05dc\u05d9 \u05e2\u05e0\u05d3\u05da \u05de\u05df \u05e1\u05d0\u05d9\u05e8 \u05d0\u05dc\u05d1\u05e6\u05d0\u05d9\u05e2 \u05d0\u05dc\u05ea\u05d9 \u05db\u05e0\u05ea \u05db\u05dc\u05e4\u05ea\u05d4\u05d0 [...]</li>\n<li>\u05d0\u05dc\u05d9 \u05d3\u05d4\u05dc\u05da \u05d0\u05df \u05e7\u05d3\u05e8\u05ea \u05e2\u05dc\u05d9 \u05d3\u05dc\u05da \u05d5\u05d0\u05df \u05dc\u05dd \u05ea\u05e7\u05d3\u05e8 \u05d9\u05e6\u05dc\u05e0\u05d9 \u05db[\u05ea\u05d0\u05d1\u05da... \u05d9\u05d5\u05e7\u05e4\u05e0\u05d9]</li>\n<li>\u05e2\u05dc\u05d9\u05d4 \u05d0\u05de\u05d0 \u05d0\u05df \u05d0\u05d2\u05d9 \u05d5\u05d0\u05d7\u05de\u05dc \u05de\u05d0 \u05dc\u05d9 \u05d5\u05dc\u05dc\u05e9\u05d9\u05da \u05d0\u05d1\u05d9 \u05d9\u05e2\u05e7\u05d5\u05d1 [\u05d0\u05dc\u05d7\u05db\u05d9\u05dd ...]</li>\n<li>\u05d5\u05d5\u05e6\u05dc\u05ea\u05e0\u05d9 \u05db\u05ea\u05d1\u05da \u05d0\u05dc\u05db\u05e8\u05d9\u05de\u05d4 \u05d1\u05de\u05d0 \u05d0\u05e0\u05ea \u05d0\u05d4\u05dc \u05dc\u05d4 \u05d5\u05e7\u05dc\u05ea \u05dc\u05d9 [...]</li>\n<li>\u05e2\u05dc\u05d9 \u05e9\u05dc\u05d5\u05dd \u05e4\u05d0\u05df \u05e8\u05d7\u05dc\u05da \u05d9\u05e6\u05dc \u05d3\u05d4\u05dc\u05da \u05d5\u05d9\u05e1\u05d1\u05e7\u05da \u05d5\u05d0\u05ea\u05db\u05dc\u05ea \u05e2\u05dc[\u05d9 \u05d0\u05dc\u05dc\u05d4 \u05ea\u05e2\u05d0\u05dc\u05d9]</li>\n<li>\u05d5\u05e2\u05dc\u05d9 \u05de\u05d5\u05dc\u05d0\u05d9 \u05d5\u05db\u05e0\u05ea \u05d0\u05e0\u05e4\u05d3\u05ea \u05de\u05e2 //\u05d1\u05df// \u05d0\u05dc\u05e0\u05d0\u05db\u05d3\u05d0\u05d4 \u05d5\u05d0\u05dc\u05d0\u05e9\u05ea\u05d9\u05d0\u05dd [...]</li>\n<li>\u05d5\u05e1\u05ea\u05d9\u05df \u05e7\u05d8\u05e2\u05d4 \u05e4\u05d5\u05dc\u05d0\u05d3 \u05d5\u05d3\u05d5\u05df \u05d0\u05dc\u05e1\u05d1\u05e2\u05d9\u05df \u05de\u05e0\u05db\u05dc \u05d0\u05dc\u05d9 \u05e2\u05e0\u05d3 \u05de\u05d5\u05dc\u05d0\u05d9 \u05d5\u05d1\u05dc\u05e1[ ...]</li>\n<li>\u05d1\u05df \u05d0\u05dc\u05d3\u05d1\u05d0\u05d2 \u05db\u05de\u05d0 \u05e2\u05dc\u05dd \u05de\u05d5\u05dc\u05d0\u05d9 \u05d5\u05ea\u05dc\u05e4\u05ea \u05d5\u05d0\u05dc\u05d0\u05df \u05d9\u05d0 \u05de\u05d5\u05dc\u05d0\u05d9 \u05d0\u05dc\u05d2\u05e8\u05e5 [\u05d0\u05dc\u05de\u05e7\u05e6\u05d5\u05d3]</li>\n<li>\u05d1\u05d4 \u05e4\u05d9 \u05d4\u05d3\u05d0 \u05d0\u05dc\u05db\u05ea\u05d0\u05d1 \u05d4\u05d5 \u05ea\u05db\u05dc\u05d9\u05e5 \u05de\u05d0 \u05d9\u05db\u05ea\u05e5 \u05d1\u05d0\u05dc\u05e9\u05d9\u05da \u05d0\u05d1\u05d9 \u05d9\u05e2\u05e7\u05d5\u05d1 \u05d0\u05dc[\u05d7\u05db\u05d9\u05dd]</li>\n<li>\u05d0\u05d3\u05d0\u05dd \u05d0\u05dc\u05dc\u05d4 \u05e2\u05d6\u05d4 \u05de\u05df \u05d2\u05de\u05d9\u05e2 \u05d7\u05d5\u05d0\u05d9\u05d2\u05d4 \u05d0\u05dc\u05de\u05db\u05ea\u05e6\u05d4 \u05d1\u05d4 \u05d5\u05e9\u05e8\u05d7\u05d4\u05d0</li>\n<li>\u05d0\u05dc\u05e1\u05d1\u05e2 \u05e7\u05d8\u05e2 \u05d0\u05dc\u05e4\u05e6\u05d4 \u05d0\u05dc\u05dc\u05d8\u05d0\u05e3 \u05d0\u05dc\u05de\u05e7\u05d3\u05dd \u05d3\u05db\u05e8\u05d4\u05d0 \u05d5\u05d5\u05d6\u05e0\u05d4\u05d0 &lt;&lt;\u05e9\u05d8\u05e0 \u05d5\u05de\u05d0 \u05e6\u05d7 \u05e4\u05d9\u05d4\u05d0&gt;&gt; \u05d5\u05d0\u05dc\u05e7\u05d8\u05e2\u05d4</li>\n<li>\u05d0\u05dc\u05d0\u05e9\u05e0\u05d4 \u05d5\u05d5\u05d6\u05e0\u05d4\u05d0 [[\u05e2\u05dc\u05d9 \u05de\u05d0 \u05d3\u05db\u05e8 \u05d0\u05dc\u05d7\u05db\u05d9\u05dd]] \u05d0\u05e8\u05d1\u05e2\u05d4 \u05de\u05d0\u05d9\u05d4 \u05de\u05e0\u05d0 //\u05d5\u05de\u05d0 \u05e6\u05d7 \u05e4\u05d9\u05d4\u05d0// [[\u05d5\u05d0\u05dc\u05de\u05e2\u05d5\u05dc]]</li>\n<li>\u05e2\u05dc\u05d9 \u05de\u05d0 \u05e6\u05d7 \u05e2\u05e0\u05d3 \u05de\u05d5\u05dc\u05d0\u05d9 \u05d5\u05d0\u05dc\u05d0\u05e4\u05ea\u05d9\u05de\u05d5\u05df \u05d5\u05d5\u05d6\u05e0\u05d4 \u05e2\u05e9\u05e8\u05d4 \u05d0\u05de\u05e0\u05d0 [[\u05e2\u05dc\u05d9 \u05de\u05d0 \u05d3\u05db\u05e8]]</li>\n<li>[[\u05d0\u05d9\u05e6\u05b9\u05d0]] \u05d5\u05d0\u05dc\u05e6\u05e8\u05d4 \u05d0\u05dc\u05e0\u05d7\u05d0\u05e1 [[\u05d3\u05db\u05e8 \u05d0\u05d9\u05e6\u05b9\u05d0 \u05d0\u05df]] \u05d5\u05d6\u05e0\u05d4\u05d0 \u05de\u05d0\u05d9\u05d4 \u05d5\u05e2\u05e9\u05e8\u05d4 \u05d0\u05e8\u05d8\u05d0\u05dc</li>\n<li>\u05d1\u05de\u05e6\u05e8 //\u05d1\u05de\u05d0 \u05db\u05d0\u05df \u05e4\u05d9\u05d4\u05d0 \u05de\u05df \u05d0\u05dc\u05e6\u05d1 \u05d5\u05d0\u05dc\u05e6\u05e8\u05d1 \u05d5\u05d1\u05e2\u05e0\u05d0 \u05de\u05e0\u05d4\u05d0 \u05d0\u05dc\u05e6\u05e8\u05d1 \u05d5\u05d0\u05d1\u05ea\u05e2\u05e0\u05d0 \u05e2\u05d5\u05e6\u05b9\u05d4 \u05d0\u05dc\u05e6\u05d1// \u05d5\u05d0\u05dc\u05de\u05d7\u05de\u05d5\u05d3\u05d4 [[\u05d3\u05db\u05e8 \u05d0\u05df]] \u05d5\u05d6\u05e0\u05d4\u05d0 \u05e2\u05e9\u05e8\u05d9\u05df \u05d3\u05e8\u05d4\u05de\u05d0 \u05d5\u05d0\u05dc\u05db\u05e8\u05e7\u05d4 \u05d0\u05dc\u05dc\u05e4\u05d0\u05e4\u05d4</li>\n<li>\u05d0\u05d9\u05e6\u05d0 \u05ea\u05d7\u05e7\u05e7 \u05d9\u05d0 \u05de\u05d5\u05dc\u05d0\u05d9 \u05d2\u05de\u05d9\u05e2 \u05de\u05d0 \u05e6\u05d7 \u05e4\u05d9 \u05d4\u05d3\u05d4 \u05d0\u05dc\u05d7\u05d5\u05d0\u05d9\u05d2 \u05d0\u05dc\u05de\u05e7\u05d3\u05dd</li>\n<li>\u05d3\u05db\u05e8\u05d4\u05d0 \u05d0\u05dc\u05de\u05db\u05ea\u05e6\u05d4 \u05d1\u05d0\u05dc\u05e9\u05d9\u05da \u05d0\u05d1\u05d9 \u05d9\u05e2\u05e7\u05d5\u05d1 \u05d0\u05dc\u05d7\u05db\u05d9\u05dd \u05d0\u05d3\u05d0\u05dd \u05d0\u05dc\u05dc\u05d4 \u05e2\u05d6\u05d4</li>\n<li>\u05d5\u05de\u05d0 \u05e6\u05d7 \u05e4\u05d9 \u05d0\u05dc\u05db\u05de\u05e1\u05d9\u05df \u05d1\u05d4\u05d0\u05e8 \u05d0\u05dc\u05e4\u05dc\u05e4\u05dc \u05d0\u05dc\u05d3\u05d9 \u05db\u05e0\u05ea \u05e1\u05d0\u05dc\u05ea\u05da \u05d0\u05dc\u05d0\u05e1\u05dc\u05d0\u05e3 \u05e2\u05dc\u05d9\u05d4\u05d0</li>\n<li>//[[\u05d5\u05e2\u05e8\u05e4\u05ea\u05da \u05d0\u05df \u05dc\u05dc\u05e9\u05d9\u05da \u05d0\u05d1\u05d9 \u05d9\u05e2\u05e7\u05d5\u05d1 \u05de\u05df \u05d2\u05de\u05dc\u05ea\u05d4\u05d0 \u05d8\u05d5]]// \u05d5\u05de\u05d0 \u05e6\u05d7 \u05e4\u05d9 \u05d0\u05dc\u05e0\u05d7\u05d0\u05e1 \u05de\u05e4\u05e8\u05d3 \u05dc\u05d0\u05e0\u05e0\u05d9 \u05e7\u05d3 \u05d3\u05e4\u05e2\u05ea \u05dc\u05d4 \u05de\u05d0\u05d9\u05ea\u05d9 \u05d3\u05d9\u05e0\u05d0\u05e8\u05d0</li>\n<li>\u05e2\u05dc\u05d9 \u05d3\u05dc\u05da \u05d5\u05e2\u05dc\u05d9 \u05de\u05d0 \u05db\u05d0\u05df \u05dc\u05d4 \u05e6\u05d7\u05d1\u05ea\u05d9 \u05d0\u05dc\u05d9 \u05e0\u05d4\u05e8 \u05d5\u05d0\u05e8\u05d4 \u05d0\u05d9\u05e6\u05d0 \u05de\u05df \u05d0\u05dc\u05de\u05d9\u05e2\u05d4</li>\n<li>\u05d5\u05d0\u05dc\u05de\u05e8\u05d2\u05d0\u05df \u05d5\u05d0\u05e0\u05d0 \u05d0\u05d2\u05d3\u05d3 \u05d0\u05dc\u05e1\u05d5\u05d0\u05dc \u05dc\u05de\u05d5\u05dc\u05d0\u05d9 \u05d0\u05dc\u05e9\u05d9\u05da \u05d0\u05d3\u05d0\u05dd \u05d0\u05dc\u05dc\u05d4 \u05ea\u05d0\u05d9\u05d9\u05d3\u05d4</li>\n<li>\u05d0\u05df \u05d9\u05d7\u05e7\u05e7 \u05dc\u05d9 \u05de\u05d0 \u05e6\u05d7 \u05e4\u05d9 \u05db\u05dc \u05d7\u05d0\u05d2\u05d4 \u05de\u05df \u05d4\u05d3\u05d4 \u05d0\u05dc\u05d7\u05d5\u05d0\u05d9\u05d2 \u05d5\u05d0\u05dc\u05e4\u05e6\u05d4 \u05db\u05dc \u05e7\u05d8\u05e2\u05d4</li>\n<li>\u05d5\u05e7\u05d8\u05e2\u05d4 \u05d1\u05d0\u05d5\u05d6\u05d0\u05e0\u05d4\u05dd \u05d5\u05d0\u05e1\u05e2\u05d0\u05e8\u05d4\u05dd \u05d5\u05d0\u05ea\u05de\u05d0\u05e0\u05d4\u05dd &lt;&lt;\u05d1\u05e2\u05d3 \u05d0\u05db\u05e8\u05d0\u05d2 \u05de\u05d0 \u05d9\u05e1\u05ea\u05d7\u05e7 \u05e2\u05dc\u05d9\u05d4 \u05de\u05df \u05de\u05db\u05e1 \u05d5\u05e2\u05de\u05d0\u05dc\u05d4 \u05d5\u05de\u05d0 \u05d0\u05e6\u05e4\u05ea\u05d4 \u05e2\u05dc\u05d9 \u05ea\u05de\u05df \u05d0\u05dc\u05e0\u05d7\u05d0\u05e1 \u05d5\u05d4\u05d5 \u05d2 \u05d3\u05e0\u05d0&gt;&gt; \u05d5\u05de\u05d0 \u05e6\u05d7 \u05e4\u05d9 \u05d0\u05dc\u05db\u05de\u05e1\u05d9\u05df</li>\n<li>\u05d1\u05d4\u05d0\u05e8 \u05d0\u05dc\u05e4\u05dc\u05e4\u05dc \u05d5\u05d9\u05ea\u05db\u05dc\u05e3 \u05dc\u05d9 \u05d0\u05dc\u05de\u05e9\u05e7\u05d4 \u05e4\u05d9 \u05e2\u05de\u05dc \u05d0\u05dc\u05d7\u05e1\u05d0\u05d1 \u05e4\u05d9 \u05d3\u05dc\u05da \u05db\u05de\u05d0</li>\n<li>\u05e2\u05d4\u05d3\u05ea \u05de\u05df \u05ea\u05e4\u05e6\u05dc\u05d4 \u05e7\u05d3\u05d9\u05de\u05d0 \u05d5\u05d7\u05d3\u05d9\u05ea\u05d0 \u05d5\u05de\u05d0 \u05db\u05d0\u05df \u05dc\u05d9 \u05dc\u05db\u05d0\u05e6\u05ea\u05d9 \u05d0\u05dc\u05d3\u05d9</li>\n<li>\u05d3\u05db\u05e8\u05ea\u05d4 \u05d7\u05e6\u05e8\u05ea\u05d4 \u05d5\u05d5\u05e6\u05dc\u05e0\u05d9 \u05d1\u05d4 \u05db\u05ea\u05d0\u05d1\u05d4 \u05d4\u05d5 \u05de\u05e7\u05d1\u05d5\u05dc \u05e2\u05e0\u05d3\u05d9 \u05d2\u05d0\u05d9\u05d6 \u05dc\u05d0 \u05d0\u05e9\u05da</li>\n<li>\u05e4\u05d9\u05d4 \u05d5\u05de\u05d0 \u05ea\u05d7\u05e7\u05e7 \u05de\u05df \u05d2\u05de\u05dc\u05d4 \u05de\u05d0 \u05d9\u05db\u05ea\u05e5 \u05d1\u05de\u05d5\u05dc\u05d0\u05d9 \u05d0\u05dc\u05e9\u05d9\u05da \u05d0\u05d1\u05d9 \u05d9\u05e2\u05e7\u05d5\u05d1</li>\n<li>\u05d0\u05dc\u05d7\u05db\u05d9\u05dd \u05d0\u05d3\u05d0\u05dd \u05d0\u05dc\u05dc\u05d4 \u05e2\u05dc\u05d0\u05d4 \u05ea\u05e0\u05e2\u05dd \u05d9\u05d0\u05de\u05d5\u05dc\u05d0\u05d9 \u05d5\u05ea\u05e9\u05ea\u05e8\u05d9 \u05d1\u05d0\u05dc\u05de\u05d1\u05dc\u05d2 \u05d1\u05e6\u05d0\u05e2\u05d4</li>\n<li>\u05ea\u05e0\u05e4\u05d3\u05d4\u05d0 \u05de\u05e2 \u05de\u05df \u05d9\u05e7\u05e2 \u05d0\u05dc\u05e8\u05d0\u05d9 \u05e2\u05dc\u05d9 \u05d0\u05d9\u05e6\u05d0\u05dc \u05d4\u05d3\u05d0 \u05d0\u05dc\u05db\u05ea\u05d0\u05d1 \u05de\u05df \u05d9\u05d3\u05d4 \u05d1\u05d5\u05db\u05d0\u05dc\u05d4</li>\n<li>\u05ea\u05db\u05ea\u05d1 \u05dc\u05d4 \u05d1\u05d0\u05de\u05e8 \u05d1\u05d9\u05ea \u05d3\u05d9\u05df \u05d5\u05d9\u05e7\u05dc\u05d3\u05e0\u05d9 \u05e4\u05d9 \u05d3\u05dc\u05da \u05d0\u05dc\u05de\u05e0\u05d4 \u05d5\u05dc\u05d0 \u05d9\u05dc\u05d7\u05e7\u05d4 \u05ea\u05d5\u05d0\u05e0\u05d9</li>\n<li>\u05e4\u05d9\u05d4 //\u05dc\u05e7\u05d1\u05e6\u05d4 \u05dc\u05d9\u05e6\u05dc \u05d0\u05dc\u05d9 \u05d1\u05d9\u05ea \u05d3\u05d9\u05df \u05dc\u05d9\u05e6\u05dc \u05db\u05dc \u05de\u05e0\u05d0 \u05d0\u05dc\u05d9 \u05d7\u05e7\u05d4// \u05d5\u05e7\u05d3 \u05db\u05e0\u05ea \u05db\u05ea\u05d1\u05ea \u05d0\u05dc\u05d9 \u05de\u05d5\u05dc\u05d0\u05d9 \u05d0\u05d3\u05d0\u05dd \u05d0\u05dc\u05dc\u05d4 \u05e2\u05d6\u05d4 \u05d5\u05e1\u05d0\u05dc\u05ea\u05d4 \u05d0\u05df \u05d9\u05e1\u05e4\u05e8</li>\n<li>\u05de\u05d0 \u05e2\u05e0\u05d3\u05d4 \u05de\u05df \u05d2\u05de\u05d9\u05e2 \u05de\u05d0 \u05d9\u05db\u05ea\u05e5 \u05d1\u05d9 \u05d5\u05d1\u05d0\u05dc\u05e9\u05d9\u05da \u05d0\u05d1\u05d9 \u05d9\u05e2\u05e7\u05d5\u05d1 \u05d0\u05dc\u05de\u05d3\u05db\u05d5\u05e8 \u05d7\u05e8\u05e1</li>\n<li>\u05d0\u05dc\u05dc\u05d4 \u05e2\u05d6\u05d4 \u05d7\u05e1\u05d1 \u05de\u05d0 \u05d9\u05e8\u05d9 \u05d1\u05e8 \u05d0\u05d5 \u05d1\u05d7\u05e8 \u05dc\u05e2\u05dc \u05d0\u05dc\u05db\u05d0\u05dc\u05e7 \u05ea\u05e2\u05d0\u05dc\u05d9 \u05d9\u05d2\u05d1\u05e8 \u05d0\u05dc\u05db\u05e1\u05d0\u05e8\u05d4</li>\n<li>\u05e4\u05d9 \u05d3\u05dc\u05da \u05d5\u05d0\u05e8\u05d2\u05d5 \u05d0\u05df \u05d9\u05db\u05d5\u05df \u05ea\u05e4\u05e6\u05dc \u05d5\u05e4\u05e2\u05dc \u05d3\u05dc\u05da \u05dc\u05d0\u05e0\u05e0\u05d9 \u05db\u05e0\u05ea \u05d0\u05d8\u05dc\u05e7\u05ea \u05dc\u05da \u05d3\u05dc\u05da</li>\n<li>\u05d5\u05d0\u05dc\u05db\u05d0\u05dc\u05e7 \u05ea\u05e2\u05d0\u05dc\u05d9 \u05d9\u05d7\u05e8\u05e1 \u05de\u05d3\u05ea\u05d4 \u05d5\u05d9\u05d8\u05d9\u05dc \u05e2\u05de\u05e8\u05d4 \u05d5\u05e2\u05de\u05e8 \u05d0\u05d5\u05dc\u05d0\u05d3\u05d4 \u05d5\u05de\u05d5\u05d0\u05dc\u05d9\u05d9</li>\n<li>\u05d0\u05db\u05d5\u05ea\u05d4 \u05d5\u05dc\u05d0 \u05d9\u05e2\u05d3\u05de\u05e0\u05d9 \u05d1\u05e7\u05d0\u05d4\u05dd \u05d5\u05d0\u05e1\u05d0\u05dc\u05d4 \u05d0\u05df \u05d9\u05ea\u05d7\u05e4\u05e0\u05d9 \u05d1\u05db\u05ea\u05d0\u05d1\u05d4</li>\n<li>\u05d0\u05dc\u05db\u05e8\u05d9\u05dd \u05de\u05e6\u05de\u05df \u05d0\u05db\u05d1\u05d0\u05e8\u05d4 \u05d5\u05d0\u05d7\u05d5\u05d0\u05dc\u05d4 \u05d5\u05d0\u05dc\u05e2\u05d0\u05e8\u05e5 \u05de\u05df \u05d7\u05d0\u05d2\u05d0\u05ea\u05d4 \u05d5\u05de\u05d4\u05de\u05d0\u05ea\u05d4</li>\n<li>\u05e4\u05d0\u05e0\u05d9 \u05d0\u05e1\u05e8 \u05d1\u05d3\u05dc\u05da \u05e4\u05e2\u05dc \u05de\u05e0\u05e2\u05de\u05d0 \u05dc\u05d0 \u05e2\u05d3\u05de\u05ea\u05d4 \u05de\u05d5\u05dc\u05d0\u05d9 \u05de\u05db\u05e6\u05d5\u05e5 \u05d1\u05d0\u05ea\u05dd</li>\n<li>\u05d0\u05dc\u05e1\u05dc\u05d0\u05dd \u05d5\u05de\u05d5\u05d0\u05dc\u05d9\u05d9 \u05d0\u05db\u05d5\u05ea\u05d4 \u05d5\u05d0\u05d5\u05dc\u05d0\u05d3\u05d4 \u05de\u05db\u05e6\u05d5\u05e6\u05d9\u05df \u05d1\u05d0\u05d2\u05dc \u05e1\u05dc\u05d0\u05dd \u05d5\u05e9\u05dc\u05d5\u05dd</li>\n<li>\u05d5\u05e1\u05d0\u05d9\u05e8 \u05d0\u05dc\u05d0\u05e6\u05d3\u05e7\u05d0 \u05d5\u05de\u05df \u05e1\u05d0\u05dc \u05e2\u05e0\u05d9 \u05d0\u05d5 \u05d9\u05e1\u05dc \u05e2\u05e0\u05d9 \u05de\u05db\u05e6\u05d5\u05e6\u05d9\u05df \u05d1\u05d0\u05d2\u05dc \u05e1\u05dc\u05d0\u05dd</li>\n<li>\u05d5\u05d0\u05d8\u05d9\u05d1 \u05ea\u05d7\u05d9\u05d4 \u05d5\u05e9\u05dc\u05d5\u05dd \u05d9\u05e9\u05e2 \u05e8\u05d1</li>\n<li>\u05d9\u05d5\u05e1\u05e3 \u05d1\u05e8 \u05d3\u05d5\u05d9\u05d3</li>\n<li>\u05e0\u05e0</li>\n</ol>",
          "format": "text/html",
          "TextInput": "rtl"
        }
      ],
      "motivation": [
        "sc:supplementing",
        "transcribing"
      ],
      "schema:position": 1
    },
    {
      "id": "https://geniza.princeton.edu/annotations/48492388-01f0-4550-98aa-41569c3d77bc/",
      "type": "Annotation",
      "created": "2023-12-09T20:44:05.685719+00:00",
      "modified": "2023-12-09T20:46:15.771340+00:00",
      "dc:source": "https://geniza.princeton.edu/sources/8/",
      "target": {
        "source": {
          "id": "https://cudl.lib.cam.ac.uk/iiif/MS-TS-00028-00022/canvas/1",
          "type": "Canvas",
          "partOf": {
            "id": "https://geniza.princeton.edu/documents/5358/iiif/manifest/"
          }
        },
        "selector": {
          "type": "FragmentSelector",
          "value": "xywh=pixel:1115.6695556640625,501.5395202636719,3459.5989990234375,12263.391143798828",
          "conformsTo": "http://www.w3.org/TR/media-frags/"
        }
      },
      "body": [
        {
          "type": "TextualBody",
          "label": "Recto",
          "value": "<p>1&ndash;7. ...</p>\n<p>8. I asked my lord to grant me an advance on fifty bah\u0101rs pepper; you agr[eed and divided the amount]</p>\n<p>9. between the boat of al-Qumm\u012b and the boat of Bihz\u0101t. We all went out in [. . .]</p>\n<p>10. and you most kindly came down (to the port) and bade me farewell in the boat, you and my lords, your brothers. [. . . I entered]</p>\n<p>11. the land of al-T\u012bz, and you have heard what happened to me in al-T\u012bz and what led [to my arrival in Nahr-]</p>\n<p>12. w\u0101ra in safety, thank God, the Exalted. I received your letter, which was sent to [Nahrw&ensp;ra together with]</p>\n<p>13. an amount of dinars. You asked me to buy for you two faylams and bd[. . .]</p>\n<p>14. of silk, red and black wrappers, \u1e6cabar\u012b cloth, and pillow cases, and if the dinars sent were not [sufficient, I should]</p>\n<p>15. advance the funds needed. I bought all you ordered with my own money. [Your dinars]</p>\n<p>16. I gave to D\u0101d\u0101, the salesman, for an additional quarter per dinar [. . . He got them back,]</p>\n<p>17. after he had sued the vizier, and they are still with him [. . . I dispatched]</p>\n<p>18. the goods for you and your brothers and put into them [bags with beads(?). I wrote to you,]</p>\n<p>19. saying: May every one of you take what he desires, and the rest will remain for me [. . . To me belong]</p>\n<p>20. also two bundles of wrappers, which I sent together with [your goods. I hope they arrive]</p>\n<p>21. safely. I informed you, my lord, that I willingly [. . . On sea]</p>\n<p>22. I experienced horrors, as you know, but you have also heard [that I arrived]&nbsp;</p>\n<p>23. &nbsp;in Mirb\u0101\u1e6d safely together with what of my goods was salvaged. I [bought you steel and]</p>\n<p>24. sent it to you (pl.) from Mirb\u0101\u1e6d, as a replacement for your (pl.) goods [lost on my voyage. I wrote]</p>\n<p>25. to you (s.), explaining my situation, and asking you to verify //the price of all// goods [. . .]</p>\n<p>26. previously mentioned, also what had been obtained for the copper in Ma&ensp;.[. . . and the cost of the 50]</p>\n<p>27. bah\u0101rs and requested you to send the 50 bah&ensp;rs of [pepper . . . together]</p>\n<p>28. with all the goods I had left with you [in your warehouse . . .]</p>\n<p>29. to Dahlak, if you could do so; and if this is not possible, you should let [me know . . .,]</p>\n<p>30. whereupon I would come and carry with me my own goods and those belonging to Sheikh Ab\u016b Ya\u02bfq\u016bb al-\u1e24ak\u012bm, [may God preserve his honored position!].</p>\n<p>31. Your precious letters with messages be&ensp;tting you, reached me, saying: [When your pepper will arrive]</p>\n<p>32. in safety, then your merchandise will get to Dahlak even before your arrival there. I put my trust in [&mdash;God, may His name be exalted!&mdash;]</p>\n<p>33. and in my lord, and sent with //the son of// the n\u0101khud\u0101 and the first mate [Ibn al-Dabb\u0101gh . . .]</p>\n<p>34. and 60 pieces of steel and less than 70 sieves to my lord, but lea[rned that . . .]</p>\n<p>35. Ibn al-Dabb\u0101gh . . . as my lord also knows, and the shipment perished.</p>",
          "format": "text/html"
        }
      ],
      "motivation": [
        "sc:supplementing",
        "translating"
      ],
      "schema:position": 1
    }
  ]
}