{
  "@context": "http://iiif.io/api/presentation/2/context.json",
  "@id": "https://geniza.princeton.edu/annotations/search/?uri=https%3A%2F%2Fcudl.lib.cam.ac.uk%2Fiiif%2FMS-TS-AR-00038-00087%2Fcanvas%2F1&manifest=https%3A%2F%2Fgeniza.princeton.edu%2Fdocuments%2F8217%2Fiiif%2Fmanifest%2F",
  "@type": "sc:AnnotationList",
  "resources": [
    {
      "id": "https://geniza.princeton.edu/annotations/9ef7162c-a4e4-434d-8401-4b0221e3825e/",
      "type": "Annotation",
      "created": "2023-12-30T19:07:59.998284+00:00",
      "modified": "2023-12-30T19:07:59.998296+00:00",
      "dc:source": "https://geniza.princeton.edu/sources/135/",
      "target": {
        "source": {
          "id": "https://cudl.lib.cam.ac.uk/iiif/MS-TS-AR-00038-00087/canvas/1",
          "type": "Canvas",
          "partOf": {
            "id": "https://geniza.princeton.edu/documents/8217/iiif/manifest/"
          }
        },
        "selector": {
          "type": "FragmentSelector",
          "value": "xywh=pixel:126.19010925292969,515.94384765625,2162.0640411376953,4643.2109375",
          "conformsTo": "http://www.w3.org/TR/media-frags/"
        }
      },
      "body": [
        {
          "type": "TextualBody",
          "label": "Recto",
          "value": "<ol>\n<li>\u0628\u0633\u0645 \u0627\u0644\u0644\u0647 \u0627\u0644\u0631\u062d\u0645\u0646 \u0627\u0644\u0631\u062d\u064a\u0645&nbsp;</li>\n<li>\u0645\u0627 \u064a\u0642\u0648\u0644 \u0633\u064a\u062f\u0646\u0627 \u0627\u0644\u0641\u0642\u064a\u0647 \u0648 \u0641\u0642\u0647 \u0627\u0644\u0644\u0647&nbsp;</li>\n<li>\u0641\u064a \u0634\u062e\u0635 \u0634\u0627\u0631\u0628 \u062f\u0648\u0627 \u0645\u0646 \u0627\u0648\u0644 \u064a\u0648\u0645 \u0648 \u0647\u0648\u0627</li>\n<li>\u0641\u064a \u0628\u064a\u062a\u0647 \u0648 \u0639\u0631\u0636 \u0639\u0631\u0636 \u0627\u062d\u0648\u062c\u0647 \u0627\u0644\u062e\u0631\u0648\u062c \u0645\u0646</li>\n<li>\u0628\u064a\u062a\u0647 \u0644\u064a\u0642\u0636\u0649 \u062d\u0627\u062c\u0629 \u0644\u0646\u0641\u0633\u0647 \u0641\u0627\u0631\u0639\u062f\u0647</li>\n<li>\u0634\u062c\u0635 \u0639\u0644\u0649 \u0627\u0644\u062f\u0648\u0627 \u0627\u0644\u0630\u0649 \u0634\u0631\u0628\u0647 \u0644\u063a\u064a\u0631</li>\n<li>\u0633\u0628\u0628 \u0644\u0631\u0639\u062f\u062a\u0647 \u0648 \u0647\u0627\u0628 \u0627\u0644\u0634\u062c\u0635 \u0634\u0649 \u0645\u0646</li>\n<li>\u0627\u0645\u0631\u0627\u0636 \u0627\u0644\u0632\u0645\u0627\u0646 \u0645\u0646 \u062c\u0647\u0629 \u0627\u0644\u0631\u0639\u062f\u0629 \u0627\u0644\u0630\u064a</li>\n<li>\u0627\u0631\u062a\u0639\u062f \u0645\u0639 \u0627\u0644\u0634\u062c\u0635 \u0627\u0644\u0630\u0649 [ [\u0627\u0644\u0631] ] \u0627\u0631\u0639\u062f\u0647 \u0644\u063a\u064a\u0631</li>\n<li>\u0633\u0628\u0628 \u0648 \u0627\u0646 \u0644\u0645 \u064a\u0643\u0648\u0646 \u062a\u0645 \u0634\u0627\u0647\u062f \u0627\u0644\u0627</li>\n<li>\u0627\u0644\u0644\u0647 \u062a\u0639\u0627\u0644\u0649 \u0627\u0641\u062a\u0646\u0627 \u0631\u062d\u0645\u0643 \u0627\u0644\u0644\u0647 \u0648 \u0627\u0644\u062d\u0645\u062f \u0644\u0644\u0647</li>\n<li>\u0648 \u0635\u0644\u0649 \u0627\u0644\u0644\u0647 \u0639\u0644\u0649 \u0633\u064a\u062f\u0646\u0627 \u0645\u062d\u0645\u062f</li>\n</ol>",
          "format": "text/html"
        }
      ],
      "motivation": [
        "sc:supplementing",
        "transcribing"
      ],
      "schema:position": 1
    },
    {
      "id": "https://geniza.princeton.edu/annotations/82bbb209-a2f2-4620-aaec-9044c9f7d7b4/",
      "type": "Annotation",
      "created": "2023-12-30T19:10:57.722789+00:00",
      "modified": "2023-12-30T19:10:57.722802+00:00",
      "dc:source": "https://geniza.princeton.edu/sources/135/",
      "target": {
        "source": {
          "id": "https://cudl.lib.cam.ac.uk/iiif/MS-TS-AR-00038-00087/canvas/1",
          "type": "Canvas",
          "partOf": {
            "id": "https://geniza.princeton.edu/documents/8217/iiif/manifest/"
          }
        },
        "selector": {
          "type": "FragmentSelector",
          "value": "xywh=pixel:164.7000732421875,547.518798828125,2101.5482177734375,4692.723876953125",
          "conformsTo": "http://www.w3.org/TR/media-frags/"
        }
      },
      "body": [
        {
          "type": "TextualBody",
          "label": "Recto",
          "value": "<ol>\n<li>In the name of God, the merciful and compassionate.&nbsp;&nbsp;</li>\n<li>What does our lord, the jurisconsult, may God grant him prosperity, say&nbsp;</li>\n<li>regarding the following. A person drank medicine and immediately collapsed&nbsp;</li>\n<li>in his house. He manifested an ailment that obliged him to leave&nbsp;</li>\n<li>his house to relieve himself. A person then frightened him&nbsp;&nbsp;</li>\n<li>concerning the medicine that he had drunk, without there being any&nbsp;</li>\n<li>reason for his fear, and the person feared some&nbsp;&nbsp;</li>\n<li>chronic illness on account of the fright that&nbsp;&nbsp;</li>\n<li>he had suffered through the person who had frightened him for no&nbsp;</li>\n<li>reason. (This is what happened), although there was no witness,&nbsp;</li>\n<li>save God, exalted is he. Grant us your opinion, may God have mercy upon you. Praise be to God&nbsp;&nbsp;</li>\n<li>and the blessings of God be upon our lord Mu\u1e25ammad&nbsp;</li>\n</ol>",
          "format": "text/html"
        }
      ],
      "motivation": [
        "sc:supplementing",
        "translating"
      ],
      "schema:position": 1
    }
  ]
}