{
  "@context": "http://iiif.io/api/presentation/2/context.json",
  "@id": "https://geniza.princeton.edu/annotations/search/?uri=https%3A%2F%2Fgeniza.princeton.edu%2Fdocuments%2F5578%2Fiiif%2Ftextblock%2F1518%2Fcanvas%2F1%2F&manifest=https%3A%2F%2Fgeniza.princeton.edu%2Fdocuments%2F5578%2Fiiif%2Fmanifest%2F",
  "@type": "sc:AnnotationList",
  "resources": [
    {
      "id": "https://geniza.princeton.edu/annotations/d68267ea-a755-4b3e-a037-3ecc68c784ab/",
      "type": "Annotation",
      "created": "2023-03-03T18:19:16.380501+00:00",
      "modified": "2023-03-03T18:19:16.380515+00:00",
      "dc:source": "https://geniza.princeton.edu/sources/13/",
      "target": {
        "source": {
          "id": "https://geniza.princeton.edu/documents/5578/iiif/textblock/1518/canvas/1/",
          "type": "Canvas",
          "partOf": {
            "id": "https://geniza.princeton.edu/documents/5578/iiif/manifest/"
          }
        },
        "selector": {
          "type": "FragmentSelector",
          "value": "xywh=pixel:84.47017669677734,82.76331329345703,543.1471939086914,419.28929901123047",
          "conformsTo": "http://www.w3.org/TR/media-frags/"
        }
      },
      "body": [
        {
          "type": "TextualBody",
          "label": "recto",
          "value": "<ol>\n<li>\n<p>\u05ea\u05de\u05d0\u05dd \u05db\u05ea\u05d0\u05d1 \u05de\u05d5\u05dc\u05d0\u05d9 \u05d0\u05dc\u05e9\u05d9\u05da \u05d0\u05d1\u05d9 \u05d9\u05d7\u05d9\u05d4</p>\n</li>\n<li>\n<p>\u05e4\u05d9 \u05db\u05ea\u05d0\u05d1\u05d4 \u05d0\u05e0\u05da \u05dc\u05dd \u05ea\u05e8\u05d2\u05e2 \u05d0\u05dc\u05d9 \u05d0\u05dc\u05e7\u05d0\u05e2\u05d4 \u05d0\u05dc\u05d3\u05d9 \u05dc\u05da \u05d0\u05dc\u05d9 \u05d0\u05e1\u05e2\u05d4</p>\n</li>\n<li>\n<p>\u05d0\u05dc\u05dc\u05d4 \u05d9\u05d5\u05e4\u05e7\u05da \u05d5\u05d0\u05dc\u05dc \u05db\u05e4\u05d9\u05d0 \u05de\u05d0 \u05d5\u05e8\u05d3 \u05d0\u05dc\u05d3\u05d9 \u05de\u05e2\u05da \u05d4\u05d3\u05d9\u05d0 \u05d9\u05d0\u05de\u05d5\u05dc\u05d0\u05d9</p>\n</li>\n<li>\n<p>\u05ea\u05e7\u05d1\u05e4\u05d4\u05d0 \u05ea\u05d0\u05db\u05d3 \u05de\u05e0\u05d4\u05d0 \u05d9 \u05ea\u05e1\u05ea\u05e2\u05de\u05dc\u05d4\u05d0 \u05d5\u05ea\u05d3\u05e4\u05e2 \u05d0\u05dc\u05d9 \u05d0\u05d1\u05d9</p>\n</li>\n<li>\n<p>\u05d0\u05dc\u05d7\u05e1\u05d9\u05df \u05d9 \u05d9\u05d7\u05de\u05dc\u05d4\u05d0 \u05dc\u05d1\u05d9\u05ea \u05d0\u05db\u05ea\u05d4 \u05e4\u05d9 \u05d0\u05dc\u05e7\u05d0\u05d4\u05e8\u05d0 \u05d5\u05ea\u05ea\u05e8\u05da \u05dc\u05d9</p>\n</li>\n<li>\n<p>\u05e2\u05e0\u05d3\u05da \u05d9 \u05d0\u05dc\u05d9 \u05d7\u05d9\u05df [\u05d5]\u05e6\u05d5\u05dc\u05d9 \u05d5\u05ea\u05d3\u05e4\u05e2 \u05d9\u05d0\u05de\u05d5\u05dc\u05d0\u05d9 \u05dc\u05d0\u05d1\u05d9 \u05d0\u05dc\u05d7\u05e1\u05d9\u05df</p>\n</li>\n<li>\n<p>\u05d9 \u05d0\u05e8\u05d8\u05d0\u05dc \u05d6\u05d1\u05d9\u05d1 \u05d1\u05dc[\u05de]\u05e6\u05e8\u05d9 \u05d9\u05d0\u05db\u05dc\u05d5\u05d4 \u05db\u05d9\u05e3 \u05d0\u05e0\u05d4 \u05de\u05d0 \u05d4\u05d5 \u05dc\u05d0\u05db\u05dc</p>\n</li>\n<li>\n<p>\u05d8\u05d9\u05d9\u05d1 \u05d5\u05dc\u05d0 \u05d5\u05d2\u05d3\u05ea \u05d0\u05e1\u05d5\u05d3 \u05e0\u05e9\u05ea\u05e8\u05d9 \u05dc\u05d4\u05dd \u05d5\u05d0\u05df \u05d9\u05db\u05d5\u05df \u05dc\u05da \u05d7\u05d0\u05d2\u05d4</p>\n</li>\n<li>\n<p>\u05ea\u05e9\u05e8\u05e4\u05e0\u05d9 \u05d1\u05d4\u05d0 \u05d5\u05d0\u05dc\u05d0\u05e6\u05d8\u05d5\u05dc \u05d0\u05dc\u05d3\u05d9 \u05de\u05df \u05e6\u05d5\u05e8 \u05d9\u05e7\u05d5\u05dc\u05d5 \u05d0\u05e0\u05d4 \u05d9\u05e6\u05dc \u05e4\u05d9</p>\n</li>\n<li>\n<p>&nbsp;\u05d4\u05d0\u05d3\u05d0 \u05d0\u05dc\u05d0\u05e6\u05d1\u05d5\u05e2 \u05ea\u05e2\u05e8\u05e4\u05e0\u05d9 \u05e1\u05e2\u05e8 \u05d0\u05dc\u05e9\u05d9\u05e9 \u05d0\u05dc\u05e9\u05d0\u05de\u05d9 \u05d0\u05dc\u05db\u05dc\u05e2</p>\n</li>\n<li>\n<p>&nbsp;\u05d5\u05d0\u05dc\u05de\u05e0\u05e7\u05d5\u05e5 \u05d5\u05d0\u05dc\u05de\u05e6\u05dc\u05d1 \u05d0\u05df \u05d5\u05d2\u05d3\u05ea \u05e9\u05d9 \u05d0\u05e9\u05ea\u05e8\u05d9\u05ea\u05d4 \u05d5\u05ea\u05d1\u05d9\u05e2 \u05dc\u05d9 \u05d0\u05dc\u05e7\u05dc\u05d9\u05dc</p>\n</li>\n<li>\n<p>&nbsp;\u05dc\u05d0\u05e1\u05d9\u05df \u05d0\u05dc\u05e8\u05d9 \u05d5\u05d2\u05d4\u05ea\u05d4 \u05de\u05e2 \u05d2\u05d0\u05e8\u05d9 \u05d4\u05d5 \u05e8\u05e4\u05d9\u05e2 \u05e7\u05e8\u05d0\u05ea \u05e2\u05dc\u05d0 \u05db\u05d0\u05e6\u05ea\u05da</p>\n</li>\n<li>\n<p>&nbsp;\u05d0\u05dc\u05e1\u05dc\u05d0\u05dd \u05d5\u05ea\u05db\u05e5 \u05e1\u05d9\u05d3\u05e0\u05d0 \u05d0\u05dc\u05e8\u05d1 \u05d0\u05dc\u05d2\u05dc\u05d9\u05dc \u05d1\u05d0\u05ea\u05dd \u05d0\u05dc\u05e1\u05dc\u05d0\u05dd \u05d5\u05ea\u05db\u05e5 \u05e1\u05d9\u05d3\u05d9</p>\n</li>\n<li>\n<p>&nbsp;\u05d0\u05dc\u05e9\u05d9\u05da \u05d0\u05d1\u05d9 \u05e1\u05dc\u05d9\u05de\u05d0\u05df \u05d5\u05d5\u05dc\u05d3\u05d4 \u05d1\u05d0\u05dc\u05e1\u05dc\u05d0\u05dd \u05d5\u05ea\u05db\u05e5 \u05e1\u05d9\u05d3\u05d9 \u05d0\u05d1\u05d9 \u05d0\u05dc\u05e4\u05e8\u05d2</p>\n</li>\n</ol>",
          "format": "text/html"
        }
      ],
      "motivation": [
        "sc:supplementing",
        "transcribing"
      ],
      "schema:position": 1
    },
    {
      "id": "https://geniza.princeton.edu/annotations/85ecbb39-1da9-4f85-8d9c-42ed36676a9e/",
      "type": "Annotation",
      "created": "2023-03-03T18:19:50.179054+00:00",
      "modified": "2023-03-03T18:19:50.179068+00:00",
      "dc:source": "https://geniza.princeton.edu/sources/13/",
      "target": {
        "source": {
          "id": "https://geniza.princeton.edu/documents/5578/iiif/textblock/1518/canvas/1/",
          "type": "Canvas",
          "partOf": {
            "id": "https://geniza.princeton.edu/documents/5578/iiif/manifest/"
          }
        },
        "selector": {
          "type": "FragmentSelector",
          "value": "xywh=pixel:644.8762817382812,82.4365463256836,97.0526123046875,418.60086822509766",
          "conformsTo": "http://www.w3.org/TR/media-frags/"
        }
      },
      "body": [
        {
          "type": "TextualBody",
          "label": "recto - right margin",
          "value": "<ol>\n<li>\n<p>\u05e6\u05d4\u05e8\u05da \u05d1\u05d0\u05dc\u05e1\u05dc\u05d0\u05dd \u05d5\u05db\u05ea\u05d0\u05d1\u05da \u05dc\u05d0 \u05ea\u05db\u05dc\u05d9\u05e0\u05d9 \u05de\u05e0\u05d4\u05d0</p>\n</li>\n</ol>",
          "format": "text/html"
        }
      ],
      "motivation": [
        "sc:supplementing",
        "transcribing"
      ],
      "schema:position": 2
    }
  ]
}