{
  "@context": "http://iiif.io/api/presentation/2/context.json",
  "@id": "https://geniza.princeton.edu/annotations/search/?uri=https%3A%2F%2Fcudl.lib.cam.ac.uk%2Fiiif%2FMS-TS-00013-J-00020-00011%2Fcanvas%2F2&manifest=https%3A%2F%2Fgeniza.princeton.edu%2Fdocuments%2F3308%2Fiiif%2Fmanifest%2F",
  "@type": "sc:AnnotationList",
  "resources": [
    {
      "id": "https://geniza.princeton.edu/annotations/f44de417-31df-445a-80a6-d33db770f68e/",
      "type": "Annotation",
      "created": "2022-10-07T01:47:12.413420+00:00",
      "modified": "2022-12-18T04:21:45.724026+00:00",
      "body": [
        {
          "type": "TextualBody",
          "label": "Verso",
          "value": "<ol>\n<li>\u05e7\u05d3 \u05d7\u05e6\u05dc\u05ea \u05dc\u05d0\u05e0\u05d4 \u05de\u05e2\u05d5\u05dc \u05d9\u05e1\u05d5\u05d9 \u05e4\u05d9\u05d4\u05d0 \u05e7\u05dc\u05d9\u05dc [ . . . . . . . . . . .</li>\n<li>\u05d4\u05d5 \u05d0\u05d5 \u05d9\u05e8\u05e1\u05dc \u05e8\u05e1\u05d5\u05dc\u05d4 \u05d5\u05d0\u05dc\u05d3\u05d9 \u05d9\u05db\u05de\u05dc \u05de\u05df \u05d0\u05dc\u05d3[\u05d9 . . . . . . . . . . .</li>\n<li>\u05e4\u05d0\u05df \u05e1\u05d4\u05dc \u05e2\u05dc\u05d9\u05da \u05d0\u05df \u05ea\u05e0\u05e4\u05d3 \u05d0\u05dc\u05d0\u05d2\u05e8\u05d4 \u05d5\u05d0\u05dc\u05d0 \u05e4\u05ea\u05db[ . . . . . . . .</li>\n<li>\u05e9\u05d9\u05da \u05d0\u05d1\u05d9 \u05d0\u05dc\u05de\u05e8\u05d2\u05d0 \u05d1\u05de\u05d0 \u05ea\u05db\u05ea\u05d0\u05e8 \u05e4\u05d4\u05d5 \u05d9\u05d3\u05e4\u05e2 \u05de\u05df \u05e2\u05e0[\u05d3\u05d4</li>\n<li>\u05d5\u05e7\u05d3 \u05db\u05e0\u05ea \u05d0\u05e2\u05dc\u05de\u05ea\u05da \u05e4\u05d9 \u05d0\u05dc\u05db\u05ea\u05d0\u05d1 \u05d0\u05dc\u05d0\u05d5\u05dc \u05d0\u05df \u05d0\u05dc\u05d0\u05d2\u05e8\u05d4 \u05ea[ . . . .</li>\n<li>\u05d3\u05e0\u05d0\u05e0\u05d9\u05e8 \u05dc\u05d0\u05df \u05db\u05ea\u05d0\u05d1\u05d4 \u05d4\u05d3\u05d0 \u05d0\u05dc\u05ea\u05e4\u05e1\u05d9\u05e8 \u05e4\u05d4\u05d5 \u05de\u05ea\u05dc \u05db\u05ea\u05d0\u05d1\u05d4</li>\n<li>\u05de\u05e6\u05d7\u05e3 \u05dc\u05d9\u05e1 \u05d9\u05e2\u05d5\u05d6 \u05d0\u05dc\u05d0 \u05d0\u05dc\u05e0\u05e7\u05d8 \u05d5\u05dc\u05de\u05d5\u05e6\u05e2\u05da \u05e2\u05e0\u05d3\u05d9 \u05ea\u05e8\u05db\u05ea</li>\n<li>\u05de\u05df \u05d3\u05dc\u05da \u05e0\u05e6\u05e3 \u05d3\u05d9\u05e0\u05e8 \u05d5\u05db\u05e0\u05ea \u05e7\u05d3 \u05d0\u05e0\u05e4\u05d3\u05ea \u05dc\u05d9 \u05e2\u05dc\u05d9 \u05d9\u05d3 \u05e8 \u05e9\u05dc\u05de\u05d4</li>\n<li>\u05e0\u05e6\u05e3 \u05d3\u05d9\u05e0\u05e8 \u05d9\u05ea\u05d1\u05e7\u05d9\u05df \u05d3\u05d9\u05e0\u05e8\u05d9\u05df \u05e4\u05dc\u05d0 \u05ea\u05d5\u05db\u05e8\u05d4\u05d0 \u05e2\u05e0\u05d9 [[\u05ea\u05db\u05e5]]</li>\n<li>\u05d0\u05d5 \u05db\u05ea\u05d0\u05d1\u05da \u05dc\u05e8 \u05e9\u05dc\u05de\u05d4 \u05d1\u05d0\u05df \u05d9\u05d3\u05e4\u05e2\u05d4\u05d0 \u05e2\u05e0\u05da \u05d5\u05d9\u05e6\u05d9\u05e4\u05d4\u05d0</li>\n<li>\u05d0\u05dc\u05d9 \u05ea\u05de\u05df \u05d0\u05dc\u05e8\u05e7\u05d5\u05e7 \u05e4\u05db\u05d9\u05e3 \u05dc\u05d4 \u05d1\u05d7\u05d0\u05d2\u05d4 \u05d5\u05db\u05d3\u05de\u05d4 \u05dc\u05da \u05d5\u05d4\u05d5 \u05e9\u05d0\u05db\u05e8</li>\n<li>\u05e0\u05d0\u05e9\u05e8 \u05db\u05ea\u05d9\u05e8 \u05dc\u05d7\u05e6\u05e8\u05ea\u05da \u05d5\u05dc\u05dc\u05e9\u05d9\u05da \u05d0\u05d1\u05d9 \u05d0\u05dc\u05e2\u05dc\u05d0 \u05ea\u05db\u05e5 \u05e0\u05e4\u05e1\u05da</li>\n<li>\u05d1\u05d0\u05dc\u05e1\u05dc\u05d0\u05dd \u05d5\u05d0\u05dc\u05e9\u05d9\u05da \u05d0\u05d1\u05d9 \u05d0\u05dc\u05e2\u05dc\u05d0 \u05d0\u05dc\u05e1\u05dc\u05d0\u05dd \u05d5\u05d0\u05dc\u05de\u05e2\u05dc\u05dd</li>\n<li>\u05d0\u05dc\u05e1\u05dc\u05d0\u05dd \u05d5\u05de\u05d5\u05d0\u05dc\u05d9\u05d9 \u05d0\u05dc\u05e1\u05d0\u05d3\u05d4 \u05d0\u05dc\u05e4\u05ea\u05d9\u05d0\u05df \u05d9\u05d1\u05d5\u05e8\u05db\u05d5 \u05de\u05df \u05d4\u05e9\u05de\u05d9\u05dd</li>\n<li>\u05d0\u05dc\u05e1\u05dc\u05d0\u05dd \u05d5\u05e0\u05e9\u05ea\u05d4\u05d9 \u05de\u05d8\u05d0\u05e2\u05d3\u05ea\u05db\u05dd \u05d2\u05de\u05d9\u05e2 \u05e4\u05d9 \u05ea\u05d7\u05e6\u05d9\u05dc \u05d0\u05dc\u05de\u05d5\u05d0\u05d2\u05d9\u05e8</li>\n<li>\u05d5\u05d0\u05df \u05d0\u05ea\u05e4\u05e7 \u05dc\u05db\u05dd \u05d0\u05d9\u05e6\u05d0 \u05de\u05e0\u05d0\u05e4\u05d7 \u05ea\u05d7\u05e6\u05dc\u05d5\u05d4\u05dd \u05d5\u05ea\u05e2\u05dc\u05de\u05d5\u05e0\u05d0</li>\n<li>\u05d1\u05d7\u05e6\u05d5\u05dc\u05d4\u05dd \u05e4\u05d9 \u05db\u05ea\u05d0\u05d1 \u05e6\u05d7\u05d1\u05d4 \u05d4\u05d3\u05d0 \u05d0\u05dc\u05d2\u05d5\u05d9 \u05de\u05d5\u05e6\u05dc \u05d4\u05d3\u05d4 \u05d0\u05dc\u05d0\u05d7\u05e8\u05e3 \u05d0\u05d5</li>\n<li>\u05de\u05e2 \u05de\u05df \u05d9\u05e1\u05d4\u05dc \u05d5\u05d0\u05df \u05d7\u05e6\u05e8\u05d4 \u05dc\u05db\u05dd \u05d7\u05d0\u05d2\u05d4 \u05ea\u05d1\u05e2\u05ea\u05d5\u05d4\u05d0 \u05de\u05e2 \u05d0\u05dc\u05d2\u05d5\u05d9</li>\n<li>\u05e4\u05d4\u05d5 \u05ea\u05e7\u05d4 \u05d5\u05e9\u05dc\u05d5\u05dd</li>\n</ol>",
          "format": "text/html",
          "TextInput": "rtl"
        }
      ],
      "target": {
        "source": {
          "id": "https://cudl.lib.cam.ac.uk/iiif/MS-TS-00013-J-00020-00011/canvas/2",
          "type": "Canvas",
          "partOf": {
            "id": "https://geniza.princeton.edu/documents/3308/iiif/manifest/",
            "type": "Manifest"
          }
        },
        "selector": {
          "type": "FragmentSelector",
          "value": "xywh=percent:1,1,98,98",
          "conformsTo": "http://www.w3.org/TR/media-frags/"
        }
      },
      "dc:source": "https://geniza.princeton.edu/sources/757/",
      "motivation": [
        "sc:supplementing",
        "transcribing"
      ],
      "schema:position": 4
    },
    {
      "id": "https://geniza.princeton.edu/annotations/5cf619c2-c35b-4a4d-a58f-4ac4af08a157/",
      "type": "Annotation",
      "created": "2022-10-07T01:47:12.420293+00:00",
      "modified": "2022-12-18T04:21:38.311446+00:00",
      "body": [
        {
          "type": "TextualBody",
          "label": "Verso - bottom margin, in another hand",
          "value": "<p>\u05d5\u05e7\u05d3 \u05e9 . . . \u05e2\u05d0\u05df . .</p>",
          "format": "text/html",
          "TextInput": "rtl"
        }
      ],
      "target": {
        "source": {
          "id": "https://cudl.lib.cam.ac.uk/iiif/MS-TS-00013-J-00020-00011/canvas/2",
          "type": "Canvas",
          "partOf": {
            "id": "https://geniza.princeton.edu/documents/3308/iiif/manifest/",
            "type": "Manifest"
          }
        },
        "selector": {
          "type": "FragmentSelector",
          "value": "xywh=percent:1,1,98,98",
          "conformsTo": "http://www.w3.org/TR/media-frags/"
        }
      },
      "dc:source": "https://geniza.princeton.edu/sources/757/",
      "motivation": [
        "sc:supplementing",
        "transcribing"
      ],
      "schema:position": 5
    },
    {
      "id": "https://geniza.princeton.edu/annotations/3a0e789d-f038-489a-a404-38cf04fb7fcd/",
      "type": "Annotation",
      "created": "2022-10-07T01:47:12.427157+00:00",
      "modified": "2022-12-18T04:20:47.393899+00:00",
      "body": [
        {
          "type": "TextualBody",
          "label": "Verso - address",
          "value": "<p>\u05d9\u05e6\u05dc \u05d4\u05d3\u05d0 \u05d0\u05dc\u05db\u05ea\u05d0\u05d1 \u05d0\u05dc\u05d9 \u05de\u05d5\u05dc\u05d0\u05d9 \u05d0\u05dc\u05e9\u05d9\u05da \u05d0\u05d1\u05d9 \u05d0\u05dc\u05d1\u05e9\u05e8 \u05de\u05d7\u05d1\u05da</p>\n<p>\u05db\u05d2\u05e7 \u05de\u05e8 \u05d5\u05e8 \u05de\u05d1\u05e9\u05e8 \u05d4\u05db\u05d4\u05df \u05d1\u05d9\u05e8 \u05e1\u05dc\u05de\u05d0\u05df \u05e0\u05e2 \u05d6\u05db\u05d0\u05d9 \u05d1\u05d9\u05e8</p>\n<p>\u05d0\u05dc\u05e6\u05d0\u05de\u05df \u05d1\u05d1\u05d0\u05d1 \u05e0\u05db\u05d5 . . \u05d1\u05df \u05d0\u05dc\u05e2\u05d8\u05d0\u05dc</p>",
          "format": "text/html",
          "TextInput": "rtl"
        }
      ],
      "target": {
        "source": {
          "id": "https://cudl.lib.cam.ac.uk/iiif/MS-TS-00013-J-00020-00011/canvas/2",
          "type": "Canvas",
          "partOf": {
            "id": "https://geniza.princeton.edu/documents/3308/iiif/manifest/",
            "type": "Manifest"
          }
        },
        "selector": {
          "type": "FragmentSelector",
          "value": "xywh=percent:1,1,98,98",
          "conformsTo": "http://www.w3.org/TR/media-frags/"
        }
      },
      "dc:source": "https://geniza.princeton.edu/sources/757/",
      "motivation": [
        "sc:supplementing",
        "transcribing"
      ],
      "schema:position": 6
    },
    {
      "id": "https://geniza.princeton.edu/annotations/3276d2b7-c1b8-46dc-ab4d-7ac75cdd8b24/",
      "type": "Annotation",
      "created": "2022-10-07T01:47:12.433951+00:00",
      "modified": "2022-12-18T04:21:23.427499+00:00",
      "body": [
        {
          "type": "TextualBody",
          "label": "Verso - address (in the second hand)",
          "value": "<p>\u05d9\u05e6\u05dc \u05d4\u05d3\u05d0 \u05d0\u05dc\u05db\u05ea\u05d0\u05d1 \u05d0\u05dc\u05d9 \u05de\u05d5\u05dc\u05d0\u05d9 \u05d0\u05dc\u05e9\u05d9\u05da \u05d0\u05d1\u05d5</p>\n<p>\u05d0\u05dc\u05d1\u05e9\u05e8 \u05de\u05e2 \u05e8 \u05de\u05d1\u05d5\u05e8\u05da \u05d1\u05e8 \u05e9\u05e9\u05dc\u05de\u05d4(!)</p>\n<p>\u05e9[ . . . . . . . . ]\u05d0</p>",
          "format": "text/html",
          "TextInput": "rtl"
        }
      ],
      "target": {
        "source": {
          "id": "https://cudl.lib.cam.ac.uk/iiif/MS-TS-00013-J-00020-00011/canvas/2",
          "type": "Canvas",
          "partOf": {
            "id": "https://geniza.princeton.edu/documents/3308/iiif/manifest/",
            "type": "Manifest"
          }
        },
        "selector": {
          "type": "FragmentSelector",
          "value": "xywh=percent:1,1,98,98",
          "conformsTo": "http://www.w3.org/TR/media-frags/"
        }
      },
      "dc:source": "https://geniza.princeton.edu/sources/757/",
      "motivation": [
        "sc:supplementing",
        "transcribing"
      ],
      "schema:position": 7
    }
  ]
}